ondilo/__init__.py
ondilo/ondilo.py
ondilo-0.5.0.dist-info/LICENSE.txt
ondilo-0.5.0.dist-info/METADATA
ondilo-0.5.0.dist-info/WHEEL
ondilo-0.5.0.dist-info/top_level.txt
ondilo-0.5.0.dist-info/RECORD
