Metadata-Version: 2.1
Name: ondilo
Version: 0.5.0
Summary: A client to access Ondilo ICO APIs
Home-page: https://github.com/JeromeHXP/ondilo
Author: Jérôme Mainguet
Author-email: dartdoka@mainguet.fr
License: MIT
Platform: UNKNOWN
Classifier: Programming Language :: Python :: 3
Classifier: License :: OSI Approved :: MIT License
Classifier: Operating System :: OS Independent
Requires-Python: >=3.6
